cross_compile_tool/Dockerfile
cross_compile_tool/__init__.py
cross_compile_tool/__main__.py
cross_compile_tool/build.py
cross_compile_tool/dev.Dockerfile
cross_compile_tool/toolchain.cmake
cross_compile_tool-0.1.2.dist-info/METADATA
cross_compile_tool-0.1.2.dist-info/WHEEL
cross_compile_tool-0.1.2.dist-info/entry_points.txt
cross_compile_tool-0.1.2.dist-info/top_level.txt
cross_compile_tool-0.1.2.dist-info/RECORD
