Metadata-Version: 2.4
Name: cross-compile-tool
Version: 0.1.2
Summary: A generic fast cross-compilation tool using Docker and Sysroots
Author-email: Benjamin Tan <tan.benjaminkx@gmail.com>
Keywords: ros2,cross-compilation,docker,sysroot,arm64,aarch64
Classifier: Development Status :: 4 - Beta
Classifier: Intended Audience :: Developers
Classifier: License :: OSI Approved :: Apache Software License
Classifier: Programming Language :: Python :: 3
Classifier: Topic :: Software Development :: Build Tools
Requires-Python: >=3.8
Provides-Extra: ros
Requires-Dist: lark; extra == "ros"
Requires-Dist: catkin_pkg; extra == "ros"
Requires-Dist: empy; extra == "ros"
